odoo10_addon_purchase_operating_unit-10.0.1.1.1-py2.7-nspkg.pth
odoo/addons/purchase_operating_unit/README.rst
odoo/addons/purchase_operating_unit/__init__.py
odoo/addons/purchase_operating_unit/__manifest__.py
odoo/addons/purchase_operating_unit/demo/purchase_order_demo.xml
odoo/addons/purchase_operating_unit/models/__init__.py
odoo/addons/purchase_operating_unit/models/invoice.py
odoo/addons/purchase_operating_unit/models/procurement.py
odoo/addons/purchase_operating_unit/models/purchase.py
odoo/addons/purchase_operating_unit/security/purchase_security.xml
odoo/addons/purchase_operating_unit/static/description/icon.png
odoo/addons/purchase_operating_unit/tests/__init__.py
odoo/addons/purchase_operating_unit/tests/test_po_security.py
odoo/addons/purchase_operating_unit/tests/test_purchase_operating_unit.py
odoo/addons/purchase_operating_unit/views/purchase_order_line_view.xml
odoo/addons/purchase_operating_unit/views/purchase_order_view.xml
odoo10_addon_purchase_operating_unit-10.0.1.1.1.dist-info/DESCRIPTION.rst
odoo10_addon_purchase_operating_unit-10.0.1.1.1.dist-info/METADATA
odoo10_addon_purchase_operating_unit-10.0.1.1.1.dist-info/RECORD
odoo10_addon_purchase_operating_unit-10.0.1.1.1.dist-info/WHEEL
odoo10_addon_purchase_operating_unit-10.0.1.1.1.dist-info/metadata.json
odoo10_addon_purchase_operating_unit-10.0.1.1.1.dist-info/namespace_packages.txt
odoo10_addon_purchase_operating_unit-10.0.1.1.1.dist-info/top_level.txt
